wearablehrv/__init__.py
wearablehrv/data.py
wearablehrv/group.py
wearablehrv/individual.py
wearablehrv-0.2.1.dist-info/LICENSE
wearablehrv-0.2.1.dist-info/METADATA
wearablehrv-0.2.1.dist-info/WHEEL
wearablehrv-0.2.1.dist-info/top_level.txt
wearablehrv-0.2.1.dist-info/RECORD
