Metadata-Version: 2.1
Name: wearablehrv
Version: 0.2.1
Summary: Wearablehrv: A Python package for the validation of heart rate and heart rate variability in wearables.
Home-page: https://github.com/AminSinichi/wearable-hrv
Author: Amin Sinichi
Author-email: aminsinichi@gmail.com
License: UNKNOWN
Platform: UNKNOWN
Classifier: Programming Language :: Python :: 3
Classifier: License :: OSI Approved :: MIT License
Classifier: Operating System :: OS Independent
Requires-Python: >=3.6
Requires-Dist: pandas
Requires-Dist: numpy
Requires-Dist: plotly
Requires-Dist: pooch
Requires-Dist: matplotlib
Requires-Dist: ipywidgets
Requires-Dist: IPython
Requires-Dist: hrv-analysis
Requires-Dist: avro-python3
Requires-Dist: pingouin
Requires-Dist: seaborn
Requires-Dist: statsmodels
Requires-Dist: scipy
Requires-Dist: astropy <6.0
